CHANGES.rst
DESCRIPTION.rst
LICENSE
MANIFEST.in
README.md
setup.py
src/ldc_doc/__init__.py
src/ldc_doc/class_lister.py
src/ldc_doc.egg-info/PKG-INFO
src/ldc_doc.egg-info/SOURCES.txt
src/ldc_doc.egg-info/dependency_links.txt
src/ldc_doc.egg-info/entry_points.txt
src/ldc_doc.egg-info/requires.txt
src/ldc_doc.egg-info/top_level.txt
src/ldc_doc/pretrain/__init__.py
src/ldc_doc/pretrain/_doc.py